tfdatamap/__init__.py
tfdatamap/callback.py
tfdatamap/download.js
tfdatamap/plot.py
tfdatamap/selected.js
tfdatamap-1.0.9.dist-info/METADATA
tfdatamap-1.0.9.dist-info/WHEEL
tfdatamap-1.0.9.dist-info/top_level.txt
tfdatamap-1.0.9.dist-info/RECORD
