Metadata-Version: 2.1
Name: tfdatamap
Version: 1.0.9
Summary: A implementation of the datamap shown in "Dataset Cartography: Mapping and Diagnosing Datasets with Training Dynamics"
Home-page: https://gitlab.com/sdurobotics/medical/datamap
Author: Simon L. B. Sørensen
Author-email: siso@mmmi.sdu.dk
License: MIT
Platform: UNKNOWN
Classifier: Programming Language :: Python :: 3
Classifier: License :: OSI Approved :: MIT License
Classifier: Operating System :: OS Independent
Requires-Python: >=3.6
Requires-Dist: h5py
Requires-Dist: numpy
Requires-Dist: tensorflow-gpu
Requires-Dist: bokeh
Requires-Dist: matplotlib
